README.md
setup.py
tap_revinate/__init__.py
tap_revinate/schemas.py
tap_revinate.egg-info/PKG-INFO
tap_revinate.egg-info/SOURCES.txt
tap_revinate.egg-info/dependency_links.txt
tap_revinate.egg-info/entry_points.txt
tap_revinate.egg-info/requires.txt
tap_revinate.egg-info/top_level.txt