Metadata-Version: 1.1
Name: tap-revinate
Version: 1.0.0
Summary: Singer.io tap for extracting data from the Revinate Porter API
Home-page: http://www.singer.io
Author: Bytecode IO
Author-email: UNKNOWN
License: UNKNOWN
Platform: UNKNOWN
Classifier: Programming Language :: Python :: 3 :: Only
